<compatibility-matrix version="1.0" type="framework">
    <hal format="hidl" optional="true">
        <name>com.fingerprints.extension</name>
        <version>1.0</version>
        <interface>
            <name>IFingerprintEngineering</name>
            <instance>default</instance>
        </interface>
        <interface>
            <name>IFingerprintNavigation</name>
            <instance>default</instance>
        </interface>
        <interface>
            <name>IFingerprintSensorTest</name>
            <instance>default</instance>
        </interface>
    </hal>
    <hal format="hidl" optional="true">
        <name>com.motorola.hardware.biometric.fingerprint</name>
        <version>1.0</version>
        <interface>
            <name>IMotoFingerPrint</name>
            <instance>default</instance>
        </interface>
        <interface>
            <name>IMotoFingerPrintSensorTest</name>
            <instance>default</instance>
        </interface>
    </hal>
    <hal format="hidl" optional="true">
        <name>com.motorola.hardware.display.panel</name>
        <version>1.0</version>
        <interface>
            <name>IDisplayPanel</name>
            <instance>default</instance>
        </interface>
    </hal>
    <hal format="hidl" optional="true">
        <name>motorola.hardware.camera.imgtuner</name>
        <version>1.0</version>
        <interface>
            <name>IImageTuning</name>
            <instance>default</instance>
        </interface>
    </hal>
    <hal format="hidl" optional="true">
        <name>motorola.hardware.fdrcontrol</name>
        <version>1.0-2</version>
        <interface>
            <name>IFdrControl</name>
            <instance>default</instance>
        </interface>
    </hal>
    <hal format="hidl" optional="true">
        <name>motorola.hardware.health</name>
        <version>2.0</version>
        <interface>
            <name>IMotHealth</name>
            <instance>default</instance>
        </interface>
    </hal>
    <hal format="hidl" optional="true">
        <name>motorola.hardware.vibrator</name>
        <version>1.0</version>
        <interface>
            <name>IMotVibrator</name>
            <instance>default</instance>
        </interface>
    </hal>
    <hal format="hidl" optional="true">
        <name>motorola.hardware.wifi.supplicant</name>
        <version>1.0-1</version>
        <interface>
            <name>ISupplicantMot</name>
            <instance>default</instance>
        </interface>
    </hal>
    <hal format="hidl" optional="true">
        <name>vendor.egistec.hardware.fingerprint</name>
        <version>2.0</version>
        <interface>
            <name>IBiometricsFingerprintEts</name>
            <instance>default</instance>
        </interface>
    </hal>
    <hal format="hidl" optional="true">
        <name>vendor.nxp.nxpnfc</name>
        <version>2.0</version>
        <interface>
            <name>INxpNfc</name>
            <instance>default</instance>
        </interface>
    </hal>
</compatibility-matrix>
